pandas_profiling_manual/__init__.py
pandas_profiling_manual/pandasProfilingManual.py
pandas_profiling_manual-0.1.0.dist-info/LICENSE
pandas_profiling_manual-0.1.0.dist-info/METADATA
pandas_profiling_manual-0.1.0.dist-info/WHEEL
pandas_profiling_manual-0.1.0.dist-info/top_level.txt
pandas_profiling_manual-0.1.0.dist-info/RECORD
